lunchable_primelunch/__about__.py
lunchable_primelunch/__init__.py
lunchable_primelunch/__main__.py
lunchable_primelunch/cli.py
lunchable_primelunch/primelunch.py
lunchable_primelunch/py.typed
lunchable_primelunch-1.1.0.dist-info/METADATA
lunchable_primelunch-1.1.0.dist-info/WHEEL
lunchable_primelunch-1.1.0.dist-info/entry_points.txt
lunchable_primelunch-1.1.0.dist-info/licenses/LICENSE
lunchable_primelunch-1.1.0.dist-info/RECORD
