Metadata-Version: 2.4
Name: lunchable-primelunch
Version: 1.1.0
Summary: LunchMoney Amazon Transaction Updater
Project-URL: Documentation, https://juftin.github.io/lunchable-primelunch
Project-URL: Issues, https://github.com/juftin/lunchable-primelunch/issues
Project-URL: Source, https://github.com/juftin/lunchable-primelunch
Author-email: Justin Flannery <juftin@juftin.com>
License-Expression: MIT
License-File: LICENSE
Classifier: Development Status :: 5 - Production/Stable
Classifier: Operating System :: OS Independent
Classifier: Programming Language :: Python
Classifier: Programming Language :: Python :: 3.9
Classifier: Programming Language :: Python :: 3.10
Classifier: Programming Language :: Python :: 3.11
Classifier: Programming Language :: Python :: 3.12
Classifier: Programming Language :: Python :: 3.13
Classifier: Programming Language :: Python :: Implementation :: CPython
Classifier: Programming Language :: Python :: Implementation :: PyPy
Requires-Python: <4,>=3.9
Requires-Dist: click
Requires-Dist: lunchable>=1.2.1
Requires-Dist: pandas
Requires-Dist: rich
